<?xml version="1.0" encoding="utf-8"?>
<IcaoFboItems total="2"
xmlns="http://server.fseconomy.net"
xmlns:xsi="http://www.w3.org/2001/XMLSchema-instance"
xmlns:schemaLocation="http://server.fseconomy.net/static/xsd/datafeed_fbos.xsd"
>
<FBO>
<FboId>2515</FboId>
<Status>Active</Status>
<Airport>Buochs</Airport>
<Name>Badenflug Buochs (LSZC)</Name>
<Owner>Badenflug(carbonex)</Owner>
<Icao>LSMU</Icao>
<Location>Buochs, Buochs, Switzerland</Location>
<Lots>2</Lots>
<RepairShop>Yes</RepairShop>
<Gates>6</Gates>
<GatesRented>0</GatesRented>
<Fuel100LL>61073</Fuel100LL>
<FuelJetA>6721</FuelJetA>
<BuildingMaterials>0</BuildingMaterials>
<Supplies>0</Supplies>
<SuppliesPerDay>60</SuppliesPerDay>
<SuppliedDays>0</SuppliedDays>
<SellPrice>0.00</SellPrice>
</FBO>
<FBO>
<FboId>22390</FboId>
<Status>Active</Status>
<Airport>Buochs</Airport>
<Name>Skytrack Switzerland - Buochs (LSZC)</Name>
<Owner>Skytrack Switzerland(Aves)</Owner>
<Icao>LSMU</Icao>
<Location>Buochs, Buochs, Switzerland</Location>
<Lots>1</Lots>
<RepairShop>Yes</RepairShop>
<Gates>3</Gates>
<GatesRented>0</GatesRented>
<Fuel100LL>17179</Fuel100LL>
<FuelJetA>1</FuelJetA>
<BuildingMaterials>2000</BuildingMaterials>
<Supplies>0</Supplies>
<SuppliesPerDay>30</SuppliesPerDay>
<SuppliedDays>0</SuppliedDays>
<SellPrice>0.00</SellPrice>
</FBO>
<FBO>
<Status>Active</Status>
<Airport>Buochs</Airport>
<Name>System</Name>
<Owner>System</Owner>
<Icao>LSMU</Icao>
<Location>Buochs, Buochs, Switzerland</Location>
<Lots>N/A</Lots>
<RepairShop>Yes</RepairShop>
<Gates>N/A</Gates>
<GatesRented>N/A</GatesRented>
<Fuel100LL>Unlimited</Fuel100LL>
<FuelJetA>Unlimited</FuelJetA>
<BuildingMaterials>Unlimited</BuildingMaterials>
<Supplies>Unlimited</Supplies>
<SuppliesPerDay>N/A</SuppliesPerDay>
<SuppliedDays>N/A</SuppliedDays>
<SellPrice>N/A</SellPrice>
</FBO>
</IcaoFboItems>


